onetrack/TrackingData.py
onetrack/__init__.py
onetrack/file_utils.py
onetrack/plotting_utils.py
onetrack/tracking_utils.py
onetrack-0.0.2.dist-info/LICENSE.md
onetrack-0.0.2.dist-info/METADATA
onetrack-0.0.2.dist-info/WHEEL
onetrack-0.0.2.dist-info/top_level.txt
onetrack-0.0.2.dist-info/RECORD
