Metadata-Version: 2.1
Name: onetrack
Version: 0.0.2
Summary: A simple evaluation tool for particle tracking
Home-page: https://github.com/murnanedaniel/onetrack
Author: Daniel Murnane & Xiangyang Ju
License: Apache License, Version 2.0
Keywords: machine learning,MLOps,Pytorch,PytorchLightning,Lightning,pipeline
Platform: UNKNOWN
License-File: LICENSE.md
Requires-Dist: numpy
Requires-Dist: scipy
Requires-Dist: pandas
Requires-Dist: matplotlib
Requires-Dist: sklearn
Requires-Dist: pyyaml (>=5.1)
Requires-Dist: torch
Requires-Dist: tqdm
